{"version":1,"resource":"file:///home/sam/sam/dev/projects/portfolio/projects/citizen-project/index.html","entries":[{"id":"HOdX.html","source":"undoRedo.source","timestamp":1744209456357},{"id":"Rljl.html","timestamp":1744209466171},{"id":"ytt5.html","source":"undoRedo.source","timestamp":1744209472498},{"id":"9ccv.html","timestamp":1744209532721},{"id":"yxdi.html","timestamp":1744209550234},{"id":"GcLc.html","timestamp":1744209675727},{"id":"5rcU.html","timestamp":1744209741318},{"id":"Oo3P.html","timestamp":1744209783173},{"id":"ks7t.html","timestamp":1744209966524},{"id":"hxyC.html","timestamp":1744210071526},{"id":"ifZq.html","timestamp":1744210381912},{"id":"tx8z.html","timestamp":1744210428263},{"id":"2mAp.html","timestamp":1744210458003},{"id":"b7CV.html","timestamp":1744210487315},{"id":"jYV7.html","timestamp":1744210501530},{"id":"nvDj.html","timestamp":1744210517677},{"id":"Rlsk.html","timestamp":1744210710886},{"id":"QSSN.html","timestamp":1744210764096},{"id":"b81r.html","timestamp":1744210787576},{"id":"5rRH.html","timestamp":1744210806637},{"id":"MAOk.html","timestamp":1744211032258},{"id":"BTbm.html","timestamp":1744211101080},{"id":"ASur.html","timestamp":1744211116349},{"id":"cJob.html","timestamp":1744211144045},{"id":"QiNi.html","timestamp":1744211237729},{"id":"ti3X.html","timestamp":1744211257099},{"id":"kSH5.html","timestamp":1744211273545},{"id":"xwXG.html","timestamp":1744211291002},{"id":"QfRG.html","timestamp":1744211331979},{"id":"Mh9z.html","timestamp":1744211448075},{"id":"0RAN.html","timestamp":1744211483662},{"id":"mC7a.html","timestamp":1744211535381},{"id":"UXry.html","timestamp":1744211568776},{"id":"Lzlf.html","timestamp":1744211607250},{"id":"mZEb.html","timestamp":1744211656113},{"id":"EKds.html","timestamp":1744211673211},{"id":"sbzx.html","timestamp":1744211736730},{"id":"8zf2.html","timestamp":1744211764210},{"id":"8LvZ.html","timestamp":1744211798456},{"id":"j2Wz.html","timestamp":1744211808728},{"id":"0WVX.html","timestamp":1744211862614},{"id":"2v1J.html","timestamp":1744211899718},{"id":"g81P.html","timestamp":1744211912662},{"id":"8Y5e.html","timestamp":1744212691000},{"id":"8Jyy.html","timestamp":1744212718266},{"id":"kSm9.html","timestamp":1744212766801},{"id":"UjdL.html","timestamp":1744212805315},{"id":"X8vA.html","source":"undoRedo.source","timestamp":1744212808649},{"id":"0JRX.html","timestamp":1744212831053},{"id":"tjCt.html","timestamp":1744217154899}]}